dataclasses-stubs/METADATA.toml
dataclasses-stubs/__init__.pyi
types_dataclasses-0.6.5.dist-info/METADATA
types_dataclasses-0.6.5.dist-info/WHEEL
types_dataclasses-0.6.5.dist-info/top_level.txt
types_dataclasses-0.6.5.dist-info/RECORD
