Metadata-Version: 2.1
Name: types-dataclasses
Version: 0.6.5
Summary: Typing stubs for dataclasses
Home-page: https://github.com/python/typeshed
License: Apache-2.0 license
Project-URL: GitHub, https://github.com/python/typeshed
Project-URL: Changes, https://github.com/typeshed-internal/stub_uploader/blob/main/data/changelogs/dataclasses.md
Project-URL: Issue tracker, https://github.com/python/typeshed/issues
Project-URL: Chat, https://gitter.im/python/typing
Platform: UNKNOWN
Classifier: License :: OSI Approved :: Apache Software License
Classifier: Typing :: Stubs Only
